HNSCPred/Validation.py
HNSCPred/__init__.py
HNSCPred/hnscc/__init__.py
HNSCPred/hnscc/keras_metadata.pb
HNSCPred/hnscc/saved_model.pb
HNSCPred/hnscc/variables/variables.data-00000-of-00001
HNSCPred/hnscc/variables/variables.index
HNSCPred/hpv/__init__.py
HNSCPred/hpv/keras_metadata.pb
HNSCPred/hpv/saved_model.pb
HNSCPred/hpv/variables/variables.data-00000-of-00001
HNSCPred/hpv/variables/variables.index
HNSCPred-0.0.8.dist-info/LICENSE.txt
HNSCPred-0.0.8.dist-info/METADATA
HNSCPred-0.0.8.dist-info/WHEEL
HNSCPred-0.0.8.dist-info/top_level.txt
HNSCPred-0.0.8.dist-info/RECORD
