Metadata-Version: 2.1
Name: HNSCPred
Version: 0.0.8
Summary: A computational approach tool to predict Head and Neck Cancer affected patients from their single cell RNA seq data.
Author: Akanksha Jarwal and Aman Srivastava
Author-email: <akanksha20331@iiitd.ac.in>
License: UNKNOWN
Keywords: python,Head and neck cancer,Diagnosis,Single cell,Genomics
Platform: UNKNOWN
Classifier: Development Status :: 1 - Planning
Classifier: Intended Audience :: Developers
Classifier: Programming Language :: Python :: 3
Classifier: Operating System :: Unix
Classifier: Operating System :: MacOS :: MacOS X
Classifier: Operating System :: Microsoft :: Windows
Requires-Dist: pandas
Requires-Dist: numpy
Requires-Dist: tensorflow
Requires-Dist: keras
